{"trial_id": "0041", "hyperparameters": {"space": [{"class_name": "Int", "config": {"name": "num_dense_layers", "default": null, "conditions": [], "min_value": 1, "max_value": 3, "step": 1, "sampling": "linear"}}, {"class_name": "Int", "config": {"name": "num_units_0", "default": null, "conditions": [], "min_value": 128, "max_value": 512, "step": 128, "sampling": "linear"}}, {"class_name": "Int", "config": {"name": "num_units_1", "default": null, "conditions": [], "min_value": 64, "max_value": 256, "step": 64, "sampling": "linear"}}, {"class_name": "Int", "config": {"name": "num_units_2", "default": null, "conditions": [], "min_value": 32, "max_value": 128, "step": 32, "sampling": "linear"}}], "values": {"num_dense_layers": 3, "num_units_0": 256, "num_units_1": 128, "num_units_2": 64}}, "metrics": {"metrics": {"loss": {"direction": "min", "observations": [{"value": [0.11418753862380981], "step": 8}]}, "accuracy": {"direction": "max", "observations": [{"value": [0.9575625061988831], "step": 8}]}, "val_loss": {"direction": "min", "observations": [{"value": [0.2641696631908417], "step": 8}]}, "val_accuracy": {"direction": "max", "observations": [{"value": [0.918749988079071], "step": 8}]}}}, "score": 0.918749988079071, "best_step": 8, "status": "COMPLETED", "message": null}